smartbill/__init__.py
smartbill/authenticate.py
smartbill/config.py
smartbill/invoice.py
smartbill/stock.py
smartbill_sdk-0.2.6.dist-info/METADATA
smartbill_sdk-0.2.6.dist-info/RECORD
smartbill_sdk-0.2.6.dist-info/WHEEL
smartbill_sdk-0.2.6.dist-info/top_level.txt
